{
  "main": {
    "id": "8303b92e5c7ad3df",
    "type": "split",
    "children": [
      {
        "id": "0063e1996b47a115",
        "type": "tabs",
        "children": [
          {
            "id": "20dff7fddfeab85c",
            "type": "leaf",
            "state": {
              "type": "markdown",
              "state": {
                "file": "Meta/Todo.md",
                "mode": "source",
                "backlinks": false,
                "source": false
              }
            }
          }
        ]
      }
    ],
    "direction": "vertical"
  },
  "left": {
    "id": "d9aeb4280a2c2d08",
    "type": "split",
    "children": [
      {
        "id": "281bb42a4e3e314b",
        "type": "tabs",
        "children": [
          {
            "id": "8a8b7a8df1df37d4",
            "type": "leaf",
            "state": {
              "type": "file-explorer",
              "state": {
                "sortOrder": "alphabetical"
              }
            }
          },
          {
            "id": "697d3d6b2172979e",
            "type": "leaf",
            "state": {
              "type": "search",
              "state": {
                "query": "",
                "matchingCase": true,
                "explainSearch": false,
                "collapseAll": false,
                "extraContext": false,
                "sortOrder": "alphabetical"
              }
            }
          },
          {
            "id": "397342d7f4bdf654",
            "type": "leaf",
            "state": {
              "type": "bookmarks",
              "state": {}
            }
          }
        ]
      }
    ],
    "direction": "horizontal",
    "width": 200
  },
  "right": {
    "id": "d35ca1f0df1afd36",
    "type": "split",
    "children": [
      {
        "id": "f434834d50971a90",
        "type": "tabs",
        "children": [
          {
            "id": "32870eac3e631984",
            "type": "leaf",
            "pinned": true,
            "state": {
              "type": "graph",
              "state": {},
              "pinned": true
            }
          },
          {
            "id": "96b2d9010676ffec",
            "type": "leaf",
            "state": {
              "type": "advanced-tables-toolbar",
              "state": {}
            }
          },
          {
            "id": "7947bfbe52180808",
            "type": "leaf",
            "state": {
              "type": "outline",
              "state": {
                "file": "Meta/Todo.md"
              }
            }
          },
          {
            "id": "5709b67c1ca2b6ee",
            "type": "leaf",
            "state": {
              "type": "outgoing-link",
              "state": {
                "file": "Meta/Todo.md",
                "linksCollapsed": false,
                "unlinkedCollapsed": true
              }
            }
          }
        ],
        "currentTab": 1
      }
    ],
    "direction": "horizontal",
    "width": 264.5,
    "collapsed": true
  },
  "left-ribbon": {
    "hiddenItems": {
      "switcher:Open quick switcher": false,
      "graph:Open graph view": false,
      "command-palette:Open command palette": false,
      "templates:Insert template": false,
      "homepage:Open homepage": false
    }
  },
  "active": "20dff7fddfeab85c",
  "lastOpenFiles": [
    "Science/6.Electrical/Analog/Op-Amps/Comparator Op-Amps.md",
    "University/8. sem/ACAS.md",
    "Science/6.Electrical/Analog/Op-Amps/Non-ideal Op-Amps.md",
    "Science/6.Electrical/Analog/Op-Amps/Instrumentation Amplifiers.md",
    "Science/6.Electrical/Analog/Op-Amps/Integrator Op-Amps.md",
    "Science/6.Electrical/Analog/Op-Amps/Inverting Op-Amps.md",
    "Science/6.Electrical/Analog/Op-Amps/Non-inverting Op-Amps.md",
    "Science/6.Electrical/Analog/Op-Amps/Op-Amp Converters.md",
    "Science/6.Electrical/Analog/Op-Amps/Differential Op-Amps.md",
    "Science/6.Electrical/Analog/Op-Amps/Differentiator Op-Amps.md",
    "Science/6.Electrical/Analog/Op-Amps/Bridge Amplifiers.md",
    "Science/6.Electrical/Analog/Op-Amps/Ideal Operational Amplifiers.md",
    "University/Untitled.md",
    "University/8. sem",
    "Meta/Todo.md",
    "Business/Innovation/Models and Frameworks.md",
    "Business/Innovation/AIE.md",
    "Business/Innovation/Theory of Innovation.md",
    "Business/Innovation/Business Modelling.md",
    "Business/Innovation/Negotiation.md",
    "Business/Innovation/CIS.md",
    "Business/Innovation/Teams and Cooperation.md",
    "Business/Innovation/Intellectual Property.md",
    "Science/7.Data Science/Basics/Regularization.md",
    "Science/7.Data Science/Neural Networks/Optimizers.md",
    "Science/7.Data Science/Basics/Loss-Functions.md",
    "Science/2.Mathematics/Linear Algebra/Convolution.md",
    "Business/Innovation/Untitled",
    "Business/Innovation",
    "Assets/Electronics/Power/boost_converter.svg",
    "Assets/Electronics/transformers.svg",
    "Assets/Electronics/transformers.svg",
    "Assets/Signal-Processing/2d_freq_filters.svg",
    "Assets/Signal-Processing/2d_fourier.svg",
    "Assets/Signal-Processing/fourier_2d.svg",
    "Assets/Web/xml_quad.svg",
    "Assets/Web/xml_curve.svg",
    "Assets/Web",
    "Assets/Untitled Folder",
    "Assets/Electronics/periodic_functions.svg",
    "Assets/Electronics/dc_eq_nonlin_ps.png",
    "Science/2.Mathematics/Functions",
    "Science/5.Electrical/Analog/Rectifiers",
    "Science/5.Electrical/Analog/Diodes",
    "Meta/Untitled",
    "Assets/Electronics/pn-junction 1.xml"
  ]
}